opentrafficsim/__init__.py
opentrafficsim/ots-distribution/target/ots-distribution-1.7.5.jar
opentrafficsim-1.7.5.dist-info/LICENSE.txt
opentrafficsim-1.7.5.dist-info/METADATA
opentrafficsim-1.7.5.dist-info/WHEEL
opentrafficsim-1.7.5.dist-info/RECORD
