Metadata-Version: 2.3
Name: opentrafficsim
Version: 1.7.5
Summary: Python package which includes Opentrafficsim (OTS)
License: BSD-3-Clause
Author: Cyber-Physical Systems Group, Technical University of Munich
Author-email: commonroad@lists.lrz.de
Requires-Python: >=3.8
Classifier: License :: OSI Approved :: BSD License
Classifier: Programming Language :: Python :: 3
Classifier: Programming Language :: Python :: 3.8
Classifier: Programming Language :: Python :: 3.9
Classifier: Programming Language :: Python :: 3.10
Classifier: Programming Language :: Python :: 3.11
Classifier: Programming Language :: Python :: 3.12
Classifier: Programming Language :: Python :: 3.13
